[
	{
		"firstName": "Linus",
		"lastName": "Sebastian",
		"tier": "Plus",
		"transaction": {
			"value": 100,
			"date": "20/11/2022",
			"status": "approved"
		}
	},
	{
		"firstName": "Haytham",
		"lastName": "Kenway",
		"tier": "Standard",
		"transaction": {
			"value": 69,
			"date": "20/11/2022",
			"status": "pending"
		}
	},
	{
		"firstName": "Polly",
		"lastName": "Kamann",
		"tier": "Standard",
		"transaction": {
			"value": 69,
			"date": "18/11/2022",
			"status": "approved"
		}
	},
	{
		"firstName": "Valerie",
		"lastName": "Turgeon",
		"tier": "Aucune",
		"transaction": {
			"value": 23414,
			"date": "19/11/2022",
			"status": "denied"
		}
	},
	{
		"firstName": "Theodore",
		"lastName": "l'Heureux",
		"tier": "Suprême",
		"transaction": {
			"value": 180,
			"date": "18/11/2022",
			"status": "approved"
		}
	},
	{
		"firstName": "Geralt",
		"lastName": "de Riv",
		"tier": "Aucune",
		"transaction": {
			"value": 4423,
			"date": "19/11/2022",
			"status": "approved"
		}
	},
	{
		"firstName": "Konqi",
		"lastName": "Konqueror",
		"tier": "Standard",
		"transaction": {
			"value": 69,
			"date": "19/11/2022",
			"status": "approved"
		}
	},
	{
		"firstName": "Arno",
		"lastName": "Dorian",
		"tier": "Standard",
		"transaction": {
			"value": 69,
			"date": "19/11/2022",
			"status": "approved"
		}
	},
	{
		"firstName": "Lumine",
		"lastName": "of Arwindale",
		"tier": "Suprême",
		"transaction": {
			"value": 180,
			"date": "19/11/2022",
			"status": "pending"
		}
	},
	{
		"firstName": "Ezio",
		"lastName": "Auditore da Firenze",
		"tier": "Plus",
		"transaction": {
			"value": 110,
			"date": "19/11/2022",
			"status": "approved"
		}
	}
]
